FlareUI/__init__.py
FlareUI/cli/__init__.py
FlareUI/core/__init__.py
FlareUI/core/api.py
FlareUI/core/component.py
FlareUI/core/context.py
FlareUI/core/dom.py
FlareUI/core/events.py
FlareUI/core/hooks.py
FlareUI/core/lazy.py
FlareUI/core/renderer.py
FlareUI/core/state.py
FlareUI/core/store.py
FlareUI/core/styling.py
FlareUI/core/template.py
FlareUI/router/__init__.py
FlareUI/router/hooks.py
tests/__init__.py
tests/test_component.py
flareui-0.1.0.dist-info/METADATA
flareui-0.1.0.dist-info/WHEEL
flareui-0.1.0.dist-info/top_level.txt
flareui-0.1.0.dist-info/RECORD
