Metadata-Version: 2.2
Name: flareui
Version: 0.1.0
Summary: A modern Python UI Framework
Home-page: https://github.com/yourusername/flareui
Author: Your Name
Author-email: Your Name <your.email@example.com>
Project-URL: Homepage, https://github.com/pratikacharya1234/FlareUI
Project-URL: Bug Tracker, https://github.com/pratikacharya1234/FlareUI/issues
Classifier: Programming Language :: Python :: 3
Classifier: License :: OSI Approved :: MIT License
Classifier: Operating System :: OS Independent
Requires-Python: >=3.8
Provides-Extra: dev
Requires-Dist: pytest>=7.0; extra == "dev"
Requires-Dist: black>=22.0; extra == "dev"
Requires-Dist: isort>=5.0; extra == "dev"
Requires-Dist: mypy>=1.0; extra == "dev"
Dynamic: author
Dynamic: home-page
Dynamic: requires-python
